[{"proposal":"juno_4","yes":5,"no":26,"veto":0,"abstain":11,"no_vote":78,"size":78},{"proposal":"juno_16","yes":40,"no":50,"veto":5,"abstain":26,"no_vote":15,"size":50},{"proposal":"juno_18","yes":1,"no":40,"veto":37,"abstain":20,"no_vote":32,"size":40},{"proposal":"juno_19","yes":2,"no":51,"veto":8,"abstain":22,"no_vote":44,"size":51},{"proposal":"juno_20","yes":81,"no":16,"veto":0,"abstain":15,"no_vote":22,"size":81},{"proposal":"juno_72","yes":46,"no":3,"veto":5,"abstain":29,"no_vote":44,"size":46},{"proposal":"juno_83","yes":5,"no":78,"veto":0,"abstain":15,"no_vote":32,"size":78},{"proposal":"juno_85","yes":24,"no":59,"veto":0,"abstain":15,"no_vote":32,"size":59},{"proposal":"juno_125","yes":5,"no":79,"veto":0,"abstain":22,"no_vote":27,"size":79},{"proposal":"juno_141","yes":81,"no":1,"veto":0,"abstain":25,"no_vote":27,"size":81},{"proposal":"juno_284","yes":53,"no":19,"veto":0,"abstain":36,"no_vote":27,"size":53},{"proposal":"juno_292","yes":81,"no":5,"veto":0,"abstain":21,"no_vote":27,"size":81},{"proposal":"juno_307","yes":34,"no":39,"veto":0,"abstain":34,"no_vote":27,"size":39},{"proposal":"juno_7","yes":19,"no":19,"veto":0,"abstain":10,"no_vote":73,"size":73},{"proposal":"juno_15","yes":14,"no":39,"veto":1,"abstain":29,"no_vote":43,"size":43},{"proposal":"juno_30","yes":5,"no":15,"veto":66,"abstain":4,"no_vote":40,"size":66},{"proposal":"juno_39","yes":68,"no":6,"veto":0,"abstain":38,"no_vote":23,"size":68},{"proposal":"juno_59","yes":47,"no":38,"veto":2,"abstain":24,"no_vote":23,"size":47},{"proposal":"juno_60","yes":40,"no":14,"veto":0,"abstain":55,"no_vote":25,"size":55},{"proposal":"juno_89","yes":31,"no":26,"veto":0,"abstain":46,"no_vote":30,"size":46},{"proposal":"juno_275","yes":92,"no":8,"veto":0,"abstain":17,"no_vote":20,"size":92},{"proposal":"juno_279","yes":20,"no":26,"veto":0,"abstain":59,"no_vote":28,"size":59},{"proposal":"juno_280","yes":32,"no":53,"veto":0,"abstain":20,"no_vote":28,"size":53},{"proposal":"juno_286","yes":1,"no":48,"veto":12,"abstain":44,"no_vote":28,"size":48},{"proposal":"juno_306","yes":50,"no":31,"veto":2,"abstain":19,"no_vote":31,"size":50},{"proposal":"juno_312","yes":7,"no":58,"veto":3,"abstain":11,"no_vote":47,"size":58},{"proposal":"juno_313","yes":61,"no":8,"veto":5,"abstain":15,"no_vote":41,"size":61},{"proposal":"juno_314","yes":34,"no":36,"veto":0,"abstain":24,"no_vote":36,"size":36},{"proposal":"juno_316","yes":70,"no":5,"veto":1,"abstain":15,"no_vote":39,"size":70},{"proposal":"juno_318","yes":20,"no":34,"veto":0,"abstain":22,"no_vote":48,"size":48},{"proposal":"juno_321","yes":33,"no":15,"veto":2,"abstain":49,"no_vote":35,"size":49},{"proposal":"juno_322","yes":34,"no":19,"veto":1,"abstain":43,"no_vote":36,"size":43},{"proposal":"juno_323","yes":27,"no":22,"veto":0,"abstain":49,"no_vote":35,"size":49},{"proposal":"juno_324","yes":24,"no":22,"veto":0,"abstain":52,"no_vote":35,"size":52},{"proposal":"juno_326","yes":77,"no":0,"veto":0,"abstain":23,"no_vote":33,"size":77},{"proposal":"juno_328","yes":15,"no":16,"veto":1,"abstain":54,"no_vote":43,"size":54},{"proposal":"juno_329","yes":30,"no":4,"veto":0,"abstain":51,"no_vote":44,"size":51},{"proposal":"juno_330","yes":15,"no":5,"veto":5,"abstain":54,"no_vote":49,"size":54},{"proposal":"juno_331","yes":32,"no":31,"veto":8,"abstain":26,"no_vote":36,"size":36},{"proposal":"juno_335","yes":15,"no":13,"veto":0,"abstain":58,"no_vote":43,"size":58},{"proposal":"juno_336","yes":31,"no":3,"veto":0,"abstain":53,"no_vote":42,"size":53},{"proposal":"juno_337","yes":29,"no":4,"veto":0,"abstain":51,"no_vote":45,"size":51},{"proposal":"juno_338","yes":25,"no":4,"veto":0,"abstain":57,"no_vote":43,"size":57},{"proposal":"juno_339","yes":23,"no":5,"veto":0,"abstain":58,"no_vote":44,"size":58},{"proposal":"juno_349","yes":19,"no":9,"veto":1,"abstain":59,"no_vote":41,"size":59},{"proposal":"juno_351","yes":4,"no":52,"veto":5,"abstain":7,"no_vote":51,"size":52},{"proposal":"juno_353","yes":35,"no":4,"veto":0,"abstain":25,"no_vote":53,"size":53}]